{
  "name": "Vaadin.ComboBoxItemElement",
  "tag": "vaadin-combo-box-item",
  "baseUrl": "vaadin-combo-box/vaadin-combo-box-item.html",
  "version": "3.0.0",
  "properties": [
    {
      "name": "index",
      "type": [
        "NUMBER"
      ],
      "objectType": [],
      "description": "The index of the item\n           "
    },
    {
      "name": "item",
      "type": [
        "STRING",
        "OBJECT"
      ],
      "objectType": [],
      "description": "The item to render"
    },
    {
      "name": "label",
      "type": [
        "STRING"
      ],
      "objectType": [],
      "description": "The text label corresponding to the item\n           "
    },
    {
      "name": "selected",
      "type": [
        "BOOLEAN"
      ],
      "objectType": [],
      "description": "True when item is selected\n           "
    },
    {
      "name": "focused",
      "type": [
        "BOOLEAN"
      ],
      "objectType": [],
      "description": "True when item is focused\n           "
    }
  ],
  "methods": [
    {
      "name": "connectedCallback",
      "description": "",
      "parameters": [],
      "returns": "UNDEFINED"
    }
  ],
  "events": [],
  "slots": [],
  "behaviors": [],
  "mixins": [
    "Vaadin.ThemableMixin"
  ],
  "description": "The default element used for items in the vaadin-combobox.\n\n### Styling\n\nThe following state attributes are exposed for styling:\n\nAttribute    | Description | Part name\n-------------|-------------|------------\n`selected` | Set when the item is selected | :host\n`focused` | Set when the item is focused | :host"
}
